<?xml version="1.0"?>
<!DOCTYPE hibernate-mapping PUBLIC "-//Hibernate/Hibernate Mapping DTD 3.0//EN"
"http://hibernate.sourceforge.net/hibernate-mapping-3.0.dtd">
<!-- Generated Jan 3, 2007 4:00:56 PM by Hibernate Tools 3.2.0.beta8 -->
<hibernate-mapping>
    <class name="net.sf.regadb.db.TestNominalValue" table="test_nominal_value" schema="public">
        <id name="nominalValueIi" type="java.lang.Integer">
            <column name="nominal_value_ii" />
            <generator class="sequence">
                <param name="sequence">test_nominal_value_test_nominal_value_ii_seq</param>
            </generator>
        </id>
        <version name="version" type="java.lang.Integer">
            <column name="version" />
        </version>
        <many-to-one name="testType" class="net.sf.regadb.db.TestType" fetch="select">
            <column name="test_type_ii" not-null="true" />
        </many-to-one>
        <property name="value" type="string">
            <column name="value" length="100" not-null="true" />
        </property>
    </class>
</hibernate-mapping>
